README.txt
setup.py
PY4GRID.egg-info/PKG-INFO
PY4GRID.egg-info/SOURCES.txt
PY4GRID.egg-info/dependency_links.txt
PY4GRID.egg-info/entry_points.txt
PY4GRID.egg-info/top_level.txt
org/py4grid/GP.py
org/py4grid/GPR.py
org/py4grid/__init__.py
org/py4grid/multicast/__init__.py
org/py4grid/multicast/utils.py
org/py4grid/multicast/daemons/DiscoverDaemons.py
org/py4grid/multicast/daemons/DiscoverServers.py
org/py4grid/multicast/daemons/__init__.py
org/py4grid/scripts/__init__.py
org/py4grid/scripts/discover_entrypoint.py
org/py4grid/scripts/exec.py
org/py4grid/scripts/py4gridserver_entrypoint.py