Metadata-Version: 1.1
Name: PY4GRID
Version: 1.0.2
Summary: a little framework to simule multiprocessing over a lot of computers
Home-page: UNKNOWN
Author: João Jorge Pereira Farias Junior
Author-email: joaojfarias@gmail.com
License: GPLv3+
Platform: UNKNOWN
Classifier: License :: OSI Approved :: GNU General Public License v3 or later (GPLv3+)
Classifier: Topic :: System :: Distributed Computing
Classifier: Topic :: Software Development :: Libraries :: Application Frameworks
Classifier: Programming Language :: Python :: 2
Classifier: Programming Language :: Python :: 3
